napari_czitools/__init__.py
napari_czitools/_datatreewidget.py
napari_czitools/_doublerange_slider.py
napari_czitools/_io.py
napari_czitools/_metadata_widget.py
napari_czitools/_range_widget.py
napari_czitools/_reader.py
napari_czitools/_sample_data.py
napari_czitools/_utilities.py
napari_czitools/_version.py
napari_czitools/_widget.py
napari_czitools/napari.yaml
napari_czitools/try_array_from_url.py
napari_czitools/_tests/__init__.py
napari_czitools/_tests/conftest.py
napari_czitools/_tests/test__io.py
napari_czitools/_tests/test_doublerange_slider.py
napari_czitools/_tests/test_file_changed.py
napari_czitools/_tests/test_metadata_widget.py
napari_czitools/_tests/test_range_widget.py
napari_czitools/_tests/test_reader.py
napari_czitools/_tests/test_sample_data.py
napari_czitools/_tests/test_scene_constraint.py
napari_czitools/_tests/test_type_column.py
napari_czitools/_tests/test_url_metadata.py
napari_czitools/_tests/test_utilities.py
napari_czitools/_tests/test_widget.py
napari_czitools/_tests/test_widget_comprehensive.py
napari_czitools-0.0.7.dist-info/licenses/LICENSE
napari_czitools-0.0.7.dist-info/METADATA
napari_czitools-0.0.7.dist-info/WHEEL
napari_czitools-0.0.7.dist-info/entry_points.txt
napari_czitools-0.0.7.dist-info/top_level.txt
napari_czitools-0.0.7.dist-info/RECORD
