Metadata-Version: 2.4
Name: napari-czitools
Version: 0.0.7
Summary: Plugin to read CZI image files and their metadata
Author: Sebastian Rhode
Author-email: sebrhode@gmail.com
License: 
Project-URL: Bug Tracker, https://github.com/sebi06/napari-czitools/issues
Project-URL: Documentation, https://github.com/sebi06/napari-czitools#README.md
Project-URL: Source Code, https://github.com/sebi06/napari-czitools
Project-URL: User Support, https://github.com/sebi06/napari-czitools/issues
Classifier: Development Status :: 3 - Alpha
Classifier: Framework :: napari
Classifier: Intended Audience :: Developers
Classifier: License :: OSI Approved :: MIT License
Classifier: Operating System :: Unix
Classifier: Operating System :: Microsoft :: Windows
Classifier: Programming Language :: Python
Classifier: Programming Language :: Python :: 3
Classifier: Programming Language :: Python :: 3 :: Only
Classifier: Programming Language :: Python :: 3.10
Classifier: Programming Language :: Python :: 3.11
Classifier: Programming Language :: Python :: 3.12
Classifier: Programming Language :: Python :: 3.13
Classifier: Topic :: Scientific/Engineering :: Image Processing
Requires-Python: <3.14,>=3.10
License-File: LICENSE
Requires-Dist: numpy
Requires-Dist: magicgui
Requires-Dist: qtpy
Requires-Dist: superqt
Requires-Dist: scikit-image
Requires-Dist: pyqtgraph
Requires-Dist: czitools>=0.13.0
Provides-Extra: testing
Requires-Dist: tox; extra == "testing"
Requires-Dist: pytest; extra == "testing"
Requires-Dist: pytest-cov; extra == "testing"
Requires-Dist: pytest-qt; extra == "testing"
Requires-Dist: pytest-timeout; extra == "testing"
Requires-Dist: napari; extra == "testing"
Requires-Dist: pyqt5; extra == "testing"
Dynamic: license-file
